{
  "type": "app",
  "language": "js",
  "framework": "react",
  "management": {
    "dashboards": {
      "editor": "architect"
    },
    "extensions": true,
    "formatter": true,
    "menu": true,
    "style": true,
    "traduction": true
  },
  "modules": {
    "recharts": {
      "version": "1.1.0"
    },
    "animation": {
      "version": "1.0.0"
    },
    "api": {
      "version": "1.0.0"
    },
    "chart": {
      "version": "2.0.0"
    },
    "client-authority-manager": {
      "version": "1.2.0"
    },
    "dashboarding": {
      "version": "1.0.0"
    },
    "dynamic-parameter": {
      "version": "1.1.0"
    },
    "dynamic-parameter-datepicker": {
      "version": "2.1.0"
    },
    "dynamic-parameter-selectbox": {
      "version": "2.0.0"
    },
    "formatter": {
      "version": "1.2.0"
    },
    "core-ui": {
      "version": "3.1.0"
    },
    "menu": {
      "version": "3.0.0"
    },
    "query-builder": {
      "version": "2.0.0"
    },
    "sdk": {
      "version": "1.2.1"
    },
    "store": {
      "version": "1.0.1"
    },
    "toaster": {
      "version": "1.0.0"
    },
    "translate": {
      "version": "1.0.0"
    },
    "xhr": {
      "version": "1.0.0"
    },
    "google-chart": {
      "version": "1.0.0"
    },
    "dynamic-parameter-radio": {
      "version": "1.0.0"
    },
    "dynamic-parameter-checkbox": {
      "version": "1.0.0"
    },
    "dynamic-parameter-toggle": {
      "version": "1.0.0"
    },
    "echarts": {
      "version": "1.0.0"
    },
    "chartist": {
      "version": "1.0.0"
    },
    "chartjs": {
      "version": "1.2.0"
    },
    "morris": {
      "version": "1.0.0"
    },
    "jqvmap": {
      "version": "1.0.0"
    }
  }
}
